setup.py
fuck_this_shit/__init__.py
fuck_this_shit/bubble_sort.py
fuck_this_shit.egg-info/PKG-INFO
fuck_this_shit.egg-info/SOURCES.txt
fuck_this_shit.egg-info/dependency_links.txt
fuck_this_shit.egg-info/not-zip-safe
fuck_this_shit.egg-info/top_level.txt