Metadata-Version: 1.0
Name: fuck-this-shit
Version: 0.1
Summary: The fuck_this_shit joke in the world
Home-page: http://github.com/storborg/fuck_this_shit
Author: Flying Circus
Author-email: flyingcircus@example.com
License: MIT
Platform: UNKNOWN
